{
    "name": "abgrund:abyss_altar",
    "fallback": "empty",
    "elements": [
      {
        "element": {
          "element_type": "single_pool_element",
          "projection": "rigid",
          "location": "abgrund:abyss_haus/small_1",
          "processors": "abgrund:cracked_blocks"
        },
        "weight": 1
      },
      {
        "element": {
          "element_type": "single_pool_element",
          "projection": "rigid",
          "location": "abgrund:abyss_haus/small_2",
          "processors": "abgrund:cracked_blocks"
        },
        "weight": 1
      }
    ]
  }
  